MANIFEST.in
README.rst
setup.py
scripts/tod
tod/__init__.py
tod/commands.py
tod/links.py
tod/repo.py
tod.egg-info/PKG-INFO
tod.egg-info/SOURCES.txt
tod.egg-info/dependency_links.txt
tod.egg-info/not-zip-safe
tod.egg-info/requires.txt
tod.egg-info/top_level.txt