Metadata-Version: 1.0
Name: tod
Version: 0.1
Summary: A simple dotfiles manager.  Uses symlinks and a git repo.
Home-page: https://github.com/mvliet/tod
Author: Matthew Vliet
Author-email: matt.vliet@gmail.com
License: MIT
Platform: UNKNOWN
